passwordlookup/__init__.py
passwordlookup/get_char.py
passwordlookup/password_lookup.py
passwordlookup/provider/__init__.py
passwordlookup/provider/bitwarden_store.py
passwordlookup/provider/bitwarden_store_test.py
passwordlookup/provider/crypt_util.py
passwordlookup/provider/crypt_util_test.py
passwordlookup/provider/keepass_store.py
passwordlookup/provider/keepass_store_test.py
passwordlookup/provider/session.py
passwordlookup/provider/session_test.py
passwordlookup/provider/simple_entry.py
passwordlookup/provider/store_provider.py
provider/__init__.py
provider/bitwarden_store.py
provider/bitwarden_store_test.py
provider/crypt_util.py
provider/crypt_util_test.py
provider/keepass_store.py
provider/keepass_store_test.py
provider/session.py
provider/session_test.py
provider/simple_entry.py
provider/store_provider.py
passwordlookup-0.0.2.dist-info/LICENSE.txt
passwordlookup-0.0.2.dist-info/METADATA
passwordlookup-0.0.2.dist-info/WHEEL
passwordlookup-0.0.2.dist-info/top_level.txt
passwordlookup-0.0.2.dist-info/RECORD
