Metadata-Version: 2.1
Name: passwordlookup
Version: 0.0.2
Summary: password lookup utility for looking up keepass or bitwarden passwords via a terminal session
Home-page: https://github.com/napisani/password-lookup
Author: Nick Pisani
Author-email: napisani@yahoo.com
License: UNKNOWN
Platform: UNKNOWN
Classifier: Programming Language :: Python :: 3
Classifier: License :: OSI Approved :: MIT License
Classifier: Operating System :: OS Independent
Requires-Python: >=3.6
Requires-Dist: colorama (==0.4.3)
Requires-Dist: cryptography (==3.0)
Requires-Dist: libkeepass (==0.2.0)
Requires-Dist: pycparser (==2.20)
Requires-Dist: pycrypto (==2.6.1)
Requires-Dist: pycryptodomex (==3.9.8)
Requires-Dist: pyperclip (==1.8.0)
